[
  {
    "anonymous": false,
    "inputs": [
      {
        "indexed": true,
        "internalType": "address",
        "name": "followee",
        "type": "address"
      },
      {
        "indexed": true,
        "internalType": "address",
        "name": "follower",
        "type": "address"
      }
    ],
    "name": "Follow",
    "type": "event"
  },
  {
    "anonymous": false,
    "inputs": [
      {
        "indexed": true,
        "internalType": "address",
        "name": "user",
        "type": "address"
      },
      {
        "indexed": false,
        "internalType": "string",
        "name": "tweet",
        "type": "string"
      }
    ],
    "name": "Like",
    "type": "event"
  },
  {
    "anonymous": false,
    "inputs": [
      {
        "indexed": true,
        "internalType": "address",
        "name": "user",
        "type": "address"
      },
      {
        "indexed": false,
        "internalType": "string",
        "name": "tweet",
        "type": "string"
      },
      {
        "indexed": false,
        "internalType": "string",
        "name": "newTweet",
        "type": "string"
      },
      {
        "indexed": false,
        "internalType": "uint256",
        "name": "burn",
        "type": "uint256"
      }
    ],
    "name": "NewComment",
    "type": "event"
  },
  {
    "anonymous": false,
    "inputs": [
      {
        "indexed": true,
        "internalType": "address",
        "name": "creator",
        "type": "address"
      },
      {
        "indexed": false,
        "internalType": "string",
        "name": "tweet",
        "type": "string"
      },
      {
        "indexed": false,
        "internalType": "uint256",
        "name": "burn",
        "type": "uint256"
      }
    ],
    "name": "NewTweet",
    "type": "event"
  },
  {
    "anonymous": false,
    "inputs": [
      {
        "indexed": true,
        "internalType": "address",
        "name": "previousOwner",
        "type": "address"
      },
      {
        "indexed": true,
        "internalType": "address",
        "name": "newOwner",
        "type": "address"
      }
    ],
    "name": "OwnershipTransferred",
    "type": "event"
  },
  {
    "anonymous": false,
    "inputs": [
      {
        "indexed": true,
        "internalType": "address",
        "name": "user",
        "type": "address"
      },
      {
        "indexed": false,
        "internalType": "string",
        "name": "tweet",
        "type": "string"
      },
      {
        "indexed": false,
        "internalType": "string",
        "name": "newTweet",
        "type": "string"
      },
      {
        "indexed": false,
        "internalType": "uint256",
        "name": "burn",
        "type": "uint256"
      }
    ],
    "name": "Quote",
    "type": "event"
  },
  {
    "anonymous": false,
    "inputs": [
      {
        "indexed": true,
        "internalType": "address",
        "name": "user",
        "type": "address"
      },
      {
        "indexed": false,
        "internalType": "string",
        "name": "tweet",
        "type": "string"
      },
      {
        "indexed": false,
        "internalType": "string",
        "name": "newTweet",
        "type": "string"
      },
      {
        "indexed": false,
        "internalType": "uint256",
        "name": "burn",
        "type": "uint256"
      }
    ],
    "name": "Repost",
    "type": "event"
  },
  {
    "anonymous": false,
    "inputs": [
      {
        "indexed": true,
        "internalType": "address",
        "name": "followee",
        "type": "address"
      },
      {
        "indexed": true,
        "internalType": "address",
        "name": "unfollower",
        "type": "address"
      }
    ],
    "name": "UnFollow",
    "type": "event"
  },
  {
    "anonymous": false,
    "inputs": [
      {
        "indexed": true,
        "internalType": "address",
        "name": "user",
        "type": "address"
      },
      {
        "indexed": false,
        "internalType": "string",
        "name": "tweet",
        "type": "string"
      }
    ],
    "name": "UnLike",
    "type": "event"
  },
  {
    "inputs": [],
    "name": "owner",
    "outputs": [
      {
        "internalType": "address",
        "name": "",
        "type": "address"
      }
    ],
    "stateMutability": "view",
    "type": "function"
  },
  {
    "inputs": [
      {
        "components": [
          {
            "internalType": "uint8",
            "name": "subtype",
            "type": "uint8"
          },
          {
            "internalType": "string",
            "name": "tweet",
            "type": "string"
          },
          {
            "internalType": "string",
            "name": "newTweet",
            "type": "string"
          },
          {
            "internalType": "address",
            "name": "followee",
            "type": "address"
          },
          {
            "internalType": "uint256",
            "name": "burn",
            "type": "uint256"
          }
        ],
        "internalType": "struct SimPubProtocol.Action[]",
        "name": "actions",
        "type": "tuple[]"
      }
    ],
    "name": "publishActions",
    "outputs": [],
    "stateMutability": "payable",
    "type": "function"
  },
  {
    "inputs": [],
    "name": "renounceOwnership",
    "outputs": [],
    "stateMutability": "nonpayable",
    "type": "function"
  },
  {
    "inputs": [
      {
        "internalType": "address",
        "name": "newOwner",
        "type": "address"
      }
    ],
    "name": "transferOwnership",
    "outputs": [],
    "stateMutability": "nonpayable",
    "type": "function"
  },
  {
    "inputs": [
      {
        "internalType": "address",
        "name": "token_",
        "type": "address"
      },
      {
        "internalType": "address",
        "name": "to",
        "type": "address"
      },
      {
        "internalType": "uint256",
        "name": "amount",
        "type": "uint256"
      }
    ],
    "name": "withdrawERC20Token",
    "outputs": [
      {
        "internalType": "bool",
        "name": "",
        "type": "bool"
      }
    ],
    "stateMutability": "nonpayable",
    "type": "function"
  },
  {
    "inputs": [
      {
        "internalType": "address",
        "name": "to",
        "type": "address"
      }
    ],
    "name": "withdrawETH",
    "outputs": [],
    "stateMutability": "nonpayable",
    "type": "function"
  }
]
